LICENSE
MANIFEST.in
README.rst
setup.py
django_warp/__init__.py
django_warp/admin.py
django_warp/apps.py
django_warp/forms.py
django_warp/models.py
django_warp/tests.py
django_warp/urls.py
django_warp/views.py
django_warp.egg-info/PKG-INFO
django_warp.egg-info/SOURCES.txt
django_warp.egg-info/dependency_links.txt
django_warp.egg-info/requires.txt
django_warp.egg-info/top_level.txt
django_warp/migrations/0001_initial.py
django_warp/migrations/0002_auto_20170727_0821.py
django_warp/migrations/0003_datasets_vrt.py
django_warp/migrations/0004_datasets_transparency.py
django_warp/migrations/__init__.py
django_warp/migrations/__pycache__/0001_initial.cpython-34.pyc
django_warp/migrations/__pycache__/0001_initial.cpython-35.pyc
django_warp/migrations/__pycache__/0002_auto_20170727_0821.cpython-34.pyc
django_warp/migrations/__pycache__/0002_auto_20170727_0821.cpython-35.pyc
django_warp/migrations/__pycache__/0003_datasets_vrt.cpython-34.pyc
django_warp/migrations/__pycache__/0003_datasets_vrt.cpython-35.pyc
django_warp/migrations/__pycache__/0004_datasets_transparency.cpython-34.pyc
django_warp/migrations/__pycache__/0004_datasets_transparency.cpython-35.pyc
django_warp/migrations/__pycache__/__init__.cpython-34.pyc
django_warp/migrations/__pycache__/__init__.cpython-35.pyc
django_warp/static/warp/1.png
django_warp/static/warp/ajax-loader.gif
django_warp/static/warp/gears.gif
django_warp/static/warp/loader1.gif
django_warp/static/warp/marker_1.png
django_warp/static/warp/marker_10.png
django_warp/static/warp/marker_11.png
django_warp/static/warp/marker_12.png
django_warp/static/warp/marker_13.png
django_warp/static/warp/marker_14.png
django_warp/static/warp/marker_15.png
django_warp/static/warp/marker_16.png
django_warp/static/warp/marker_17.png
django_warp/static/warp/marker_18.png
django_warp/static/warp/marker_19.png
django_warp/static/warp/marker_2.png
django_warp/static/warp/marker_20.png
django_warp/static/warp/marker_21.png
django_warp/static/warp/marker_22.png
django_warp/static/warp/marker_23.png
django_warp/static/warp/marker_24.png
django_warp/static/warp/marker_25.png
django_warp/static/warp/marker_26.png
